pipimport/__init__.py
pipimport3-0.3.1.dist-info/METADATA
pipimport3-0.3.1.dist-info/WHEEL
pipimport3-0.3.1.dist-info/top_level.txt
pipimport3-0.3.1.dist-info/RECORD
