Metadata-Version: 2.1
Name: pipimport3
Version: 0.3.1
Summary: Automatically install missing modules using pip at import time. Best used with virtualenv. Updated fork of original by Carles F. Julia.
Home-page: https://github.com/BiscuitBobby/pipimport
Author: BiscuitBobby
Author-email: simeddon@gmail.com
License: MIT
Keywords: pip virtualenv import hook
Classifier: Development Status :: 3 - Alpha
Classifier: Programming Language :: Python :: 3
Classifier: Topic :: Software Development :: Libraries
Classifier: Topic :: System :: Software Distribution
